caldus/__init__.py
caldus/tests.py
caldus-1.3.dist-info/LICENSE
caldus-1.3.dist-info/METADATA
caldus-1.3.dist-info/WHEEL
caldus-1.3.dist-info/top_level.txt
caldus-1.3.dist-info/RECORD
