Metadata-Version: 2.1
Name: caldus
Version: 1.3
Summary: Conversion of resistance values to temperatures for platinum resistors such as RTDs
Author-email: "Gunnstein T. Frøseth" <gunnstein@mailbox.org>
License: MIT License
Project-URL: repository, https://github.com/gunnstein/caldus
Classifier: License :: OSI Approved :: ISC License (ISCL)
Classifier: Operating System :: OS Independent
Classifier: Programming Language :: Python
Classifier: Topic :: Scientific/Engineering
License-File: LICENSE
Requires-Dist: numpy
